{
  "term": "external coordinate reference system",
  "termid": "1121",
  "eng": {
    "dates": [
      {
        "date": "2010-06-15 00:00:00 +0500",
        "type": "accepted"
      }
    ],
    "definition": [
      {
        "content": "coordinate reference system whose datum is independent of the object that is located by it"
      }
    ],
    "examples": [

    ],
    "id": "1121",
    "notes": [

    ],
    "release": 2.0,
    "sources": [
      {
        "origin": {
          "ref": "ISO 19130-1:2018",
          "clause": "3.25",
          "link": "https://www.iso.org/standard/66847.html"
        },
        "type": "authoritative"
      },
      {
        "origin": {
          "ref": "ISO/TS 19130:2010"
        },
        "type": "lineage",
        "status": "unspecified"
      }
    ],
    "terms": [
      {
        "type": "expression",
        "normative_status": "preferred",
        "designation": "external coordinate reference system"
      }
    ],
    "language_code": "eng",
    "entry_status": "valid",
    "review_date": "2018-09-01 00:00:00 +0500",
    "review_decision_date": "2018-09-01 00:00:00 +0500",
    "review_decision_event": "Publication of ISO 19130-1:2018(E)",
    "status": "valid"
  },
  "ara": {
    "dates": [
      {
        "date": "2010-06-15 00:00:00 +0500",
        "type": "accepted"
      }
    ],
    "definition": [
      {
        "content": "نظام إحداثيات مرجعي والذي مرجع إسناده مستقل عن الكائن الذي تم تحديده بواسطته"
      }
    ],
    "examples": [

    ],
    "id": "1121",
    "notes": [

    ],
    "release": 2.0,
    "sources": [
      {
        "origin": {
          "ref": "ISO 19130-1:2018",
          "clause": "3.25",
          "link": "https://www.iso.org/standard/66847.html"
        },
        "type": "authoritative"
      },
      {
        "origin": {
          "ref": "ISO/TS 19130:2010"
        },
        "type": "lineage",
        "status": "unspecified"
      }
    ],
    "terms": [
      {
        "type": "expression",
        "normative_status": "preferred",
        "designation": "نظام إحداثيات مرجعي خارجي"
      }
    ],
    "language_code": "ara",
    "entry_status": "valid",
    "review_date": "2018-09-01 00:00:00 +0500",
    "review_decision_date": "2018-09-01 00:00:00 +0500",
    "review_decision_event": "Publication of ISO 19130-1:2018(E)",
    "status": "valid"
  },
  "dan": null,
  "deu": {
    "dates": [
      {
        "date": "2010-06-15 00:00:00 +0500",
        "type": "accepted"
      }
    ],
    "definition": [
      {
        "content": "Koordinatenreferenzsystem, dessen Datum von darzustellenden Objekt unabhängig ist"
      }
    ],
    "examples": [

    ],
    "id": "1121",
    "notes": [

    ],
    "release": 2.0,
    "sources": [
      {
        "origin": {
          "ref": "ISO 19130-1:2018",
          "clause": "3.25",
          "link": "https://www.iso.org/standard/66847.html"
        },
        "type": "authoritative"
      },
      {
        "origin": {
          "ref": "ISO/TS 19130:2010"
        },
        "type": "lineage",
        "status": "unspecified"
      }
    ],
    "terms": [
      {
        "type": "expression",
        "normative_status": "preferred",
        "designation": "Objektkoordinatenreferenzsystem"
      }
    ],
    "language_code": "deu",
    "entry_status": "valid",
    "review_date": "2018-09-01 00:00:00 +0500",
    "review_decision_date": "2018-09-01 00:00:00 +0500",
    "review_decision_event": "Publication of ISO 19130-1:2018(E)",
    "status": "valid"
  },
  "fin": null,
  "fra": null,
  "jpn": null,
  "kor": {
    "dates": [
      {
        "date": "2010-06-15 00:00:00 +0500",
        "type": "accepted"
      }
    ],
    "definition": [
      {
        "content": "기준좌표체계에 의해 위치가 설정된 개체와 자료가 서로 독립적인 좌표 기준 체계"
      }
    ],
    "examples": [

    ],
    "id": "1121",
    "notes": [

    ],
    "release": 2.0,
    "sources": [
      {
        "origin": {
          "ref": "ISO 19130-1:2018",
          "clause": "3.25",
          "link": "https://www.iso.org/standard/66847.html"
        },
        "type": "authoritative"
      },
      {
        "origin": {
          "ref": "ISO/TS 19130:2010"
        },
        "type": "lineage",
        "status": "unspecified"
      }
    ],
    "terms": [
      {
        "type": "expression",
        "normative_status": "preferred",
        "designation": "외부 좌표 기준 체계"
      }
    ],
    "language_code": "kor",
    "entry_status": "valid",
    "review_date": "2018-09-01 00:00:00 +0500",
    "review_decision_date": "2018-09-01 00:00:00 +0500",
    "review_decision_event": "Publication of ISO 19130-1:2018(E)",
    "status": "valid"
  },
  "msa": null,
  "nld": null,
  "pol": null,
  "rus": {
    "dates": [
      {
        "date": "2010-06-15 00:00:00 +0500",
        "type": "accepted"
      }
    ],
    "definition": [
      {
        "content": "система координат, чьи исходные даты не зависят от объекта, чье местоположение описывается этой системой координат"
      }
    ],
    "examples": [

    ],
    "id": "1121",
    "notes": [

    ],
    "release": 2.0,
    "sources": [
      {
        "origin": {
          "ref": "ISO 19130-1:2018",
          "clause": "3.25",
          "link": "https://www.iso.org/standard/66847.html"
        },
        "type": "authoritative"
      },
      {
        "origin": {
          "ref": "ISO/TS 19130:2010"
        },
        "type": "lineage",
        "status": "unspecified"
      }
    ],
    "terms": [
      {
        "type": "expression",
        "normative_status": "preferred",
        "designation": "внешняя система координат"
      }
    ],
    "language_code": "rus",
    "entry_status": "valid",
    "review_date": "2018-09-01 00:00:00 +0500",
    "review_decision_date": "2018-09-01 00:00:00 +0500",
    "review_decision_event": "Publication of ISO 19130-1:2018(E)",
    "status": "valid"
  },
  "spa": {
    "dates": [
      {
        "date": "2010-06-15 00:00:00 +0500",
        "type": "accepted"
      }
    ],
    "definition": [
      {
        "content": "sistema de referencia de coordenadas cuyo datum es independiente del objeto que se localiza con él"
      }
    ],
    "examples": [

    ],
    "id": "1121",
    "notes": [

    ],
    "release": 2.0,
    "sources": [
      {
        "origin": {
          "ref": "ISO 19130-1:2018",
          "clause": "3.25",
          "link": "https://www.iso.org/standard/66847.html"
        },
        "type": "authoritative"
      },
      {
        "origin": {
          "ref": "ISO/TS 19130:2010"
        },
        "type": "lineage",
        "status": "unspecified"
      }
    ],
    "terms": [
      {
        "type": "expression",
        "normative_status": "preferred",
        "designation": "sistema de referencia de coordenadas externo"
      }
    ],
    "language_code": "spa",
    "entry_status": "valid",
    "review_date": "2018-09-01 00:00:00 +0500",
    "review_decision_date": "2018-09-01 00:00:00 +0500",
    "review_decision_event": "Publication of ISO 19130-1:2018(E)",
    "status": "valid"
  },
  "swe": {
    "dates": [
      {
        "date": "2010-06-15 00:00:00 +0500",
        "type": "accepted"
      }
    ],
    "definition": [
      {
        "content": "koordinatreferenssystem vars datum är oberoende av de objekt som det lägesbestämmer"
      }
    ],
    "examples": [

    ],
    "id": "1121",
    "notes": [

    ],
    "release": 2.0,
    "sources": [
      {
        "origin": {
          "ref": "ISO 19130-1:2018",
          "clause": "3.25",
          "link": "https://www.iso.org/standard/66847.html"
        },
        "type": "authoritative"
      },
      {
        "origin": {
          "ref": "ISO/TS 19130:2010"
        },
        "type": "lineage",
        "status": "unspecified"
      }
    ],
    "terms": [
      {
        "type": "expression",
        "normative_status": "preferred",
        "designation": "externt koordinatreferenssystem"
      }
    ],
    "language_code": "swe",
    "entry_status": "valid",
    "review_date": "2018-09-01 00:00:00 +0500",
    "review_decision_date": "2018-09-01 00:00:00 +0500",
    "review_decision_event": "Publication of ISO 19130-1:2018(E)",
    "status": "valid"
  },
  "zho": null
}