{
  "term": "irradiance",
  "termid": "1460",
  "eng": {
    "dates": [
      {
        "date": "2014-07-15 00:00:00 +0500",
        "type": "accepted"
      }
    ],
    "definition": [
      {
        "content": "electro-magnetic radiation energy per unit area per unit time"
      }
    ],
    "examples": [

    ],
    "id": "1460",
    "notes": [
      {
        "content": "The SI unit is watts per square meter (<math xmlns=\"http://www.w3.org/1998/Math/MathML\" display=\"inline\">  <mstyle displaystyle=\"true\">    <mi>“</mi>    <mi>W</mi>    <mi>”</mi>    <mo>/</mo>    <mi>”</mi>    <mi>m</mi>    <msup>      <mi>”</mi>      <mn>2</mn>    </msup>  </mstyle></math>)"
      }
    ],
    "release": 3.0,
    "sources": [
      {
        "origin": {
          "ref": "ISO/TS 19159-1:2014",
          "clause": "4.13",
          "link": "https://www.iso.org/standard/60080.html"
        },
        "type": "authoritative",
        "status": "unspecified"
      }
    ],
    "terms": [
      {
        "type": "expression",
        "normative_status": "preferred",
        "designation": "irradiance"
      }
    ],
    "language_code": "eng",
    "entry_status": "valid",
    "status": "valid"
  },
  "ara": null,
  "dan": null,
  "deu": null,
  "fin": null,
  "fra": null,
  "jpn": null,
  "kor": {
    "dates": [
      {
        "date": "2014-07-15 00:00:00 +0500",
        "type": "accepted"
      }
    ],
    "definition": [
      {
        "content": "단위 시간당 단위 구역의 전자기 방사 에너지"
      }
    ],
    "examples": [

    ],
    "id": "1460",
    "notes": [
      {
        "content": "The SI unit is watts per square meter (W/m2)"
      }
    ],
    "release": 3.0,
    "sources": [
      {
        "origin": {
          "ref": "ISO/TS 19159-1:2014",
          "clause": "4.13",
          "link": "https://www.iso.org/standard/60080.html"
        },
        "type": "authoritative",
        "status": "unspecified"
      }
    ],
    "terms": [
      {
        "type": "expression",
        "normative_status": "preferred",
        "designation": "방사 조도, 조도, 조사"
      }
    ],
    "language_code": "kor",
    "entry_status": "valid",
    "status": "valid"
  },
  "msa": {
    "dates": [
      {
        "date": "2014-07-15 00:00:00 +0500",
        "type": "accepted"
      }
    ],
    "definition": [

    ],
    "examples": [

    ],
    "id": "1460",
    "notes": [
      {
        "content": "The SI unit is watts per square meter (W/m2)"
      }
    ],
    "release": 3.0,
    "sources": [
      {
        "origin": {
          "ref": "ISO/TS 19159-1:2014",
          "clause": "4.13",
          "link": "https://www.iso.org/standard/60080.html"
        },
        "type": "authoritative",
        "status": "unspecified"
      },
      {
        "origin": {
          "ref": "Istilah ukur dan Pemetaan (DBP, 1992)"
        },
        "type": "lineage"
      }
    ],
    "terms": [
      {
        "type": "expression",
        "normative_status": "preferred",
        "designation": "kesinaran"
      }
    ],
    "language_code": "msa",
    "entry_status": "valid",
    "status": "valid"
  },
  "nld": null,
  "pol": null,
  "rus": {
    "dates": [
      {
        "date": "2014-07-15 00:00:00 +0500",
        "type": "accepted"
      }
    ],
    "definition": [
      {
        "content": "Энергия электромагнитного излучения на единицу площади за единицу времени"
      }
    ],
    "examples": [

    ],
    "id": "1460",
    "notes": [
      {
        "content": "единица Си - ватт на квадратный метр (Вт/м2)"
      }
    ],
    "release": 3.0,
    "sources": [
      {
        "origin": {
          "ref": "ISO/TS 19159-1:2014",
          "clause": "4.13",
          "link": "https://www.iso.org/standard/60080.html"
        },
        "type": "authoritative",
        "status": "unspecified"
      },
      {
        "origin": {
          "ref": "ISO/TS 19159-1:2014"
        },
        "type": "lineage"
      }
    ],
    "terms": [
      {
        "type": "expression",
        "normative_status": "preferred",
        "designation": "интенсивность излучения"
      }
    ],
    "language_code": "rus",
    "entry_status": "valid",
    "status": "valid"
  },
  "spa": {
    "dates": [
      {
        "date": "2014-07-15 00:00:00 +0500",
        "type": "accepted"
      }
    ],
    "definition": [
      {
        "content": "radiación electromagnética por unidad de superficie y unidad de tiempo"
      }
    ],
    "examples": [

    ],
    "id": "1460",
    "notes": [
      {
        "content": "La unidad en el SI son watios entre metros cuadrados (W/m2)"
      }
    ],
    "release": 3.0,
    "sources": [
      {
        "origin": {
          "ref": "ISO/TS 19159-1:2014",
          "clause": "4.13",
          "link": "https://www.iso.org/standard/60080.html"
        },
        "type": "authoritative",
        "status": "unspecified"
      }
    ],
    "terms": [
      {
        "type": "expression",
        "normative_status": "preferred",
        "designation": "irradiancia"
      }
    ],
    "language_code": "spa",
    "entry_status": "valid",
    "status": "valid"
  },
  "swe": {
    "dates": [
      {
        "date": "2014-07-15 00:00:00 +0500",
        "type": "accepted"
      }
    ],
    "definition": [
      {
        "content": "elektromagnetisk strålningsenergi per ytenhet och tidsenhet"
      }
    ],
    "examples": [

    ],
    "id": "1460",
    "notes": [
      {
        "content": "The SI unit is watts per square meter (W/m2)"
      }
    ],
    "release": 3.0,
    "sources": [
      {
        "origin": {
          "ref": "ISO/TS 19159-1:2014",
          "clause": "4.13",
          "link": "https://www.iso.org/standard/60080.html"
        },
        "type": "authoritative",
        "status": "unspecified"
      },
      {
        "origin": {
          "ref": "(Type reference to national language document)"
        },
        "type": "lineage"
      }
    ],
    "terms": [
      {
        "type": "expression",
        "normative_status": "preferred",
        "designation": "irradians"
      }
    ],
    "language_code": "swe",
    "entry_status": "valid",
    "status": "valid"
  },
  "zho": null
}