{
  "term": "engineering datum",
  "termid": "156",
  "eng": {
    "dates": [
      {
        "date": "2003-02-15 00:00:00 +0500",
        "type": "accepted"
      }
    ],
    "definition": [
      {
        "content": "datum describing the relationship of a coordinate system to a local reference"
      }
    ],
    "examples": [
      {
        "content": "A system for identifying relative positions within a few kilometres of the reference point."
      }
    ],
    "id": "156",
    "notes": [
      {
        "content": "Engineering datum excludes both geodetic and vertical datums."
      }
    ],
    "release": 1.0,
    "sources": [
      {
        "origin": {
          "ref": "ISO 19111:2019",
          "clause": "3.1.26",
          "link": "https://www.iso.org/standard/74039.html"
        },
        "type": "authoritative"
      },
      {
        "origin": {
          "ref": "ISO 19111:2003"
        },
        "type": "lineage",
        "status": "unspecified"
      }
    ],
    "terms": [
      {
        "type": "expression",
        "normative_status": "preferred",
        "designation": "engineering datum"
      },
      {
        "type": "expression",
        "designation": "local datum"
      }
    ],
    "language_code": "eng",
    "entry_status": "valid",
    "review_date": "2019-01-31 00:00:00 +0500",
    "review_decision_date": "2019-01-31 00:00:00 +0500",
    "review_decision_event": "Publication of ISO 19111:2019(E)",
    "status": "valid"
  },
  "ara": {
    "dates": [
      {
        "date": "2003-02-15 00:00:00 +0500",
        "type": "accepted"
      }
    ],
    "definition": [
      {
        "content": "مرجع إسناد يصف علاقة نظام للإحداثيات بمرجع محلي"
      }
    ],
    "examples": [
      {
        "content": "نظام لتحديد المواقع النسبية على مسافة كيلومترات قليلة من النقطة المرجعية."
      }
    ],
    "id": "156",
    "notes": [
      {
        "content": "مرجع الإسناد الهندسي يستبعد كلاً من مرجع الإسناد الجيوديسي ومرجع الإسناد الرأسي."
      }
    ],
    "release": 1.0,
    "sources": [
      {
        "origin": {
          "ref": "ISO 19111:2019",
          "clause": "3.1.26",
          "link": "https://www.iso.org/standard/74039.html"
        },
        "type": "authoritative"
      },
      {
        "origin": {
          "ref": "ISO 19111:2003"
        },
        "type": "lineage",
        "status": "unspecified"
      }
    ],
    "terms": [
      {
        "type": "expression",
        "normative_status": "preferred",
        "designation": "مرجع إسناد هندسي"
      },
      {
        "type": "expression",
        "designation": "local datum"
      }
    ],
    "language_code": "ara",
    "entry_status": "valid",
    "review_date": "2019-01-31 00:00:00 +0500",
    "review_decision_date": "2019-01-31 00:00:00 +0500",
    "review_decision_event": "Publication of ISO 19111:2019(E)",
    "status": "valid"
  },
  "dan": {
    "dates": [
      {
        "date": "2003-02-15 00:00:00 +0500",
        "type": "accepted"
      }
    ],
    "definition": [
      {
        "content": "datum, der beskriver relationen mellem et koordinatsystem og en lokal reference"
      }
    ],
    "examples": [
      {
        "content": "Et system til identifikation af relative positioner inden for få kilometer fra referencepunktet."
      }
    ],
    "id": "156",
    "notes": [
      {
        "content": "Teknisk datum udelukker både geodætiske og vertikale datummer."
      }
    ],
    "release": 1.0,
    "sources": [
      {
        "origin": {
          "ref": "ISO 19111:2019",
          "clause": "3.1.26",
          "link": "https://www.iso.org/standard/74039.html"
        },
        "type": "authoritative"
      },
      {
        "origin": {
          "ref": "ISO 19111:2003"
        },
        "type": "lineage",
        "status": "unspecified"
      }
    ],
    "terms": [
      {
        "type": "expression",
        "designation": "teknisk datum"
      }
    ],
    "language_code": "dan",
    "review_date": "2019-01-31 00:00:00 +0500",
    "review_decision_date": "2019-01-31 00:00:00 +0500",
    "review_decision_event": "Publication of ISO 19111:2019(E)"
  },
  "deu": {
    "dates": [
      {
        "date": "2003-02-15 00:00:00 +0500",
        "type": "accepted"
      }
    ],
    "definition": [
      {
        "content": "Datum, das die Beziehung eines Koordinatensystems zu einer lokalen Referenz beschreibt"
      }
    ],
    "examples": [
      {
        "content": "A system for identifying relative positions within a few kilometres of the reference point."
      }
    ],
    "id": "156",
    "notes": [
      {
        "content": "Engineering datum excludes both geodetic and vertical datums."
      }
    ],
    "release": 1.0,
    "sources": [
      {
        "origin": {
          "ref": "ISO 19111:2019",
          "clause": "3.1.26",
          "link": "https://www.iso.org/standard/74039.html"
        },
        "type": "authoritative"
      },
      {
        "origin": {
          "ref": "ISO 19111:2003"
        },
        "type": "lineage",
        "status": "unspecified"
      }
    ],
    "terms": [
      {
        "type": "expression",
        "normative_status": "preferred",
        "designation": "lokales Datum"
      },
      {
        "type": "expression",
        "designation": "local datum"
      }
    ],
    "language_code": "deu",
    "entry_status": "valid",
    "review_date": "2019-01-31 00:00:00 +0500",
    "review_decision_date": "2019-01-31 00:00:00 +0500",
    "review_decision_event": "Publication of ISO 19111:2019(E)",
    "status": "valid"
  },
  "fin": {
    "dates": [
      {
        "date": "2003-02-15 00:00:00 +0500",
        "type": "accepted"
      }
    ],
    "definition": [
      {
        "content": "paikallinen datumi, joka määritellään suppealle alueelle tai tiettyyn tilaan usein tietyksi ajaksi tiettyä tarkoitusta varten"
      }
    ],
    "examples": [
      {
        "content": "Järjestelmä, jolla määritetään suhteellisia sijainteja muutaman kilometrin etäisyydellä vertauspisteestä."
      }
    ],
    "id": "156",
    "notes": [
      {
        "content": "Geodeettista datumia ja korkeusdatumia ei käytetä paikallisen datumin yhteydessä."
      }
    ],
    "release": 1.0,
    "sources": [
      {
        "origin": {
          "ref": "ISO 19111:2019",
          "clause": "3.1.26",
          "link": "https://www.iso.org/standard/74039.html"
        },
        "type": "authoritative"
      },
      {
        "origin": {
          "ref": "ISO 19111:2003"
        },
        "type": "lineage",
        "status": "unspecified"
      }
    ],
    "terms": [
      {
        "type": "expression",
        "normative_status": "preferred",
        "designation": "erillisdatumi"
      }
    ],
    "language_code": "fin",
    "entry_status": "valid",
    "review_date": "2019-01-31 00:00:00 +0500",
    "review_decision_date": "2019-01-31 00:00:00 +0500",
    "review_decision_event": "Publication of ISO 19111:2019(E)",
    "status": "valid"
  },
  "fra": {
    "dates": [
      {
        "date": "2003-02-15 00:00:00 +0500",
        "type": "accepted"
      }
    ],
    "definition": [
      {
        "content": "référentiel décrivant la relation entre un système de coordonnées et une référence locale"
      }
    ],
    "examples": [

    ],
    "id": "156",
    "notes": [

    ],
    "release": 1.0,
    "sources": [
      {
        "origin": {
          "ref": "ISO 19111:2019",
          "clause": "3.1.26",
          "link": "https://www.iso.org/standard/74039.html"
        },
        "type": "authoritative"
      },
      {
        "origin": {
          "ref": "ISO 19111:2003"
        },
        "type": "lineage",
        "status": "unspecified"
      }
    ],
    "terms": [
      {
        "type": "expression",
        "normative_status": "preferred",
        "designation": "référentiel d'ingénierie"
      },
      {
        "type": "expression",
        "designation": "local datum"
      }
    ],
    "language_code": "fra",
    "entry_status": "valid",
    "review_date": "2019-01-31 00:00:00 +0500",
    "review_decision_date": "2019-01-31 00:00:00 +0500",
    "review_decision_event": "Publication of ISO 19111:2019(E)",
    "status": "valid"
  },
  "jpn": null,
  "kor": {
    "dates": [
      {
        "date": "2003-02-15 00:00:00 +0500",
        "type": "accepted"
      }
    ],
    "definition": [
      {
        "content": "지역 참조와 좌표 체계간의 관계를 설명하는 지역 데이텀"
      }
    ],
    "examples": [
      {
        "content": "참조 점에서 몇 km이내의 상대 위치를 인식하기 위한 시스템"
      }
    ],
    "id": "156",
    "notes": [
      {
        "content": "공학 데이텀은 측지 원점 및 수직 데이텀 모두를 배제한다."
      }
    ],
    "release": 1.0,
    "sources": [
      {
        "origin": {
          "ref": "ISO 19111:2019",
          "clause": "3.1.26",
          "link": "https://www.iso.org/standard/74039.html"
        },
        "type": "authoritative"
      },
      {
        "origin": {
          "ref": "ISO 19111:2003"
        },
        "type": "lineage",
        "status": "unspecified"
      }
    ],
    "terms": [
      {
        "type": "expression",
        "normative_status": "preferred",
        "designation": "공학 데이텀"
      }
    ],
    "language_code": "kor",
    "entry_status": "valid",
    "review_date": "2019-01-31 00:00:00 +0500",
    "review_decision_date": "2019-01-31 00:00:00 +0500",
    "review_decision_event": "Publication of ISO 19111:2019(E)",
    "status": "valid"
  },
  "msa": {
    "dates": [
      {
        "date": "2003-02-15 00:00:00 +0500",
        "type": "accepted"
      }
    ],
    "definition": [

    ],
    "examples": [
      {
        "content": "A system for identifying relative positions within a few kilometres of the reference point."
      }
    ],
    "id": "156",
    "notes": [
      {
        "content": "Engineering datum excludes both geodetic and vertical datums."
      }
    ],
    "release": 1.0,
    "sources": [
      {
        "origin": {
          "ref": "ISO 19111:2019",
          "clause": "3.1.26",
          "link": "https://www.iso.org/standard/74039.html"
        },
        "type": "authoritative"
      },
      {
        "origin": {
          "ref": "ISO 19111:2003"
        },
        "type": "lineage",
        "status": "unspecified"
      }
    ],
    "terms": [
      {
        "type": "expression",
        "normative_status": "preferred",
        "designation": "datum kejuruteraan"
      },
      {
        "type": "expression",
        "designation": "local datum"
      }
    ],
    "language_code": "msa",
    "entry_status": "valid",
    "review_date": "2019-01-31 00:00:00 +0500",
    "review_decision_date": "2019-01-31 00:00:00 +0500",
    "review_decision_event": "Publication of ISO 19111:2019(E)",
    "status": "valid"
  },
  "nld": null,
  "pol": {
    "dates": [
      {
        "date": "2003-02-15 00:00:00 +0500",
        "type": "accepted"
      }
    ],
    "definition": [
      {
        "content": "układ odniesienia opisujący związek układu współrzędnych z lokalnym odniesieniem"
      }
    ],
    "examples": [
      {
        "content": "Układ służący do identyfikowania położeń względnych w granicach kilku kilometrów od punktu odniesienia."
      }
    ],
    "id": "156",
    "notes": [
      {
        "content": "Inżynieryjny układ odniesienia zawsze różni się od geodezyjnego i wysokościowego układu odniesienia."
      }
    ],
    "release": 1.0,
    "sources": [
      {
        "origin": {
          "ref": "ISO 19111:2019",
          "clause": "3.1.26",
          "link": "https://www.iso.org/standard/74039.html"
        },
        "type": "authoritative"
      },
      {
        "origin": {
          "ref": "ISO 19111:2003"
        },
        "type": "lineage",
        "status": "unspecified"
      }
    ],
    "terms": [
      {
        "type": "expression",
        "normative_status": "preferred",
        "designation": "inżynieryjny układ odniesienia\nlokalny układ odniesienia"
      },
      {
        "type": "expression",
        "designation": "lokalny układ odniesienia"
      }
    ],
    "language_code": "pol",
    "review_date": "2019-01-31 00:00:00 +0500",
    "review_decision_date": "2019-01-31 00:00:00 +0500",
    "review_decision_event": "Publication of ISO 19111:2019(E)"
  },
  "rus": {
    "dates": [
      {
        "date": "2003-02-15 00:00:00 +0500",
        "type": "accepted"
      }
    ],
    "definition": [
      {
        "content": "даты,  описывающие взаимосвязь некоторой системы координат с локальным ориентиром"
      }
    ],
    "examples": [
      {
        "content": "Система для определения относительного положения в пределах нескольких километров от начальной точки"
      }
    ],
    "id": "156",
    "notes": [
      {
        "content": "В инженерные даты не входят геодезические и вертикальные даты"
      }
    ],
    "release": 1.0,
    "sources": [
      {
        "origin": {
          "ref": "ISO 19111:2019",
          "clause": "3.1.26",
          "link": "https://www.iso.org/standard/74039.html"
        },
        "type": "authoritative"
      },
      {
        "origin": {
          "ref": "ISO 19111:2003"
        },
        "type": "lineage",
        "status": "unspecified"
      }
    ],
    "terms": [
      {
        "type": "expression",
        "normative_status": "admitted",
        "designation": "инженерные исходные даты"
      },
      {
        "type": "expression",
        "designation": "местные даты"
      }
    ],
    "language_code": "rus",
    "entry_status": "valid",
    "review_date": "2019-01-31 00:00:00 +0500",
    "review_decision_date": "2019-01-31 00:00:00 +0500",
    "review_decision_event": "Publication of ISO 19111:2019(E)",
    "status": "valid"
  },
  "spa": {
    "dates": [
      {
        "date": "2003-02-15 00:00:00 +0500",
        "type": "accepted"
      }
    ],
    "definition": [
      {
        "content": "datum que describe la relación de un sistema de coordenadas con una referencia local"
      }
    ],
    "examples": [
      {
        "content": "EJEMPLO Un sistema para identificar posiciones relativas a pocos kilómetros del punto de referencia."
      }
    ],
    "id": "156",
    "notes": [
      {
        "content": "NOTA Los datums para ingeniería excluyen tanto los datums geodésicos como los verticales."
      }
    ],
    "release": 1.0,
    "sources": [
      {
        "origin": {
          "ref": "ISO 19111:2019",
          "clause": "3.1.26",
          "link": "https://www.iso.org/standard/74039.html"
        },
        "type": "authoritative"
      },
      {
        "origin": {
          "ref": "ISO 19111:2003"
        },
        "type": "lineage",
        "status": "unspecified"
      }
    ],
    "terms": [
      {
        "type": "expression",
        "normative_status": "preferred",
        "designation": "datum de ingeniería"
      },
      {
        "type": "expression",
        "designation": "datum local"
      }
    ],
    "language_code": "spa",
    "entry_status": "valid",
    "review_date": "2019-01-31 00:00:00 +0500",
    "review_decision_date": "2019-01-31 00:00:00 +0500",
    "review_decision_event": "Publication of ISO 19111:2019(E)",
    "status": "valid"
  },
  "swe": null,
  "zho": {
    "dates": [
      {
        "date": "2003-02-15 00:00:00 +0500",
        "type": "accepted"
      }
    ],
    "definition": [
      {
        "content": "描述局部参照与坐标系关系的基准。"
      }
    ],
    "examples": [
      {
        "content": "确定在参照点若干公里范围内相对位置的系统。"
      }
    ],
    "id": "156",
    "notes": [
      {
        "content": "工程基准不包括大地基准和高程基准。"
      }
    ],
    "release": 1.0,
    "sources": [
      {
        "origin": {
          "ref": "ISO 19111:2019",
          "clause": "3.1.26",
          "link": "https://www.iso.org/standard/74039.html"
        },
        "type": "authoritative"
      },
      {
        "origin": {
          "ref": "ISO 19111:2003"
        },
        "type": "lineage",
        "status": "unspecified"
      }
    ],
    "terms": [
      {
        "type": "expression",
        "normative_status": "preferred",
        "designation": "工程基准"
      },
      {
        "type": "expression",
        "designation": "local datum"
      }
    ],
    "language_code": "zho",
    "entry_status": "valid",
    "review_date": "2019-01-31 00:00:00 +0500",
    "review_decision_date": "2019-01-31 00:00:00 +0500",
    "review_decision_event": "Publication of ISO 19111:2019(E)",
    "status": "valid"
  }
}