{
  "term": "transport network",
  "termid": "1621",
  "eng": {
    "dates": [
      {
        "date": "2015-06-15 00:00:00 +0500",
        "type": "accepted"
      }
    ],
    "definition": [
      {
        "content": "physical network infrastructure for mobility of transport means, containing infrastructure and equipment that facilitate traffic management"
      }
    ],
    "examples": [

    ],
    "id": "1621",
    "notes": [
      {
        "content": "A transport network is associated to a specific transport mode and specific types of transport means. The road network, consisting of streets in a city may for example support several transport networks such as transport networks for pedestrians, bicycles and use private cars. The network served by a bus service is also a transport network."
      }
    ],
    "release": 4.0,
    "sources": [
      {
        "origin": {
          "ref": "ISO 19147:2015",
          "clause": "3.18",
          "link": "https://www.iso.org/standard/44874.html"
        },
        "type": "authoritative"
      }
    ],
    "terms": [
      {
        "type": "expression",
        "normative_status": "preferred",
        "designation": "transport network"
      }
    ],
    "language_code": "eng",
    "entry_status": "valid",
    "review_date": "2009-06-20 00:00:00 +0600",
    "review_decision_date": "2015-06-15 00:00:00 +0500",
    "review_decision_event": "Normal ISO processing",
    "status": "valid"
  },
  "ara": null,
  "dan": null,
  "deu": null,
  "fin": null,
  "fra": null,
  "jpn": null,
  "kor": null,
  "msa": null,
  "nld": null,
  "pol": null,
  "rus": null,
  "spa": {
    "dates": [
      {
        "date": "2015-06-15 00:00:00 +0500",
        "type": "accepted"
      }
    ],
    "definition": [
      {
        "content": "Infraestructura de red física para la movilidad de medios de transporte, que contiene la infraestructura y el equipamiento que facilitan la gestión del tráfico"
      }
    ],
    "examples": [

    ],
    "id": "1621",
    "notes": [
      {
        "content": "Una red de transporte está asociada a un modo de transporte específico y a tipos específicos de medios de transporte. La red de carreteras, que en la ciudad se compone de calles puede, por ejemplo, permitir varias redes de transporte, tales como redes de transporte para peatones, bicicletas o coches de uso privado. La red disponible de un servicio de autobuses es también una red de transporte."
      }
    ],
    "release": 4.0,
    "sources": [
      {
        "origin": {
          "ref": "ISO 19147:2015",
          "clause": "3.18",
          "link": "https://www.iso.org/standard/44874.html"
        },
        "type": "authoritative"
      }
    ],
    "terms": [
      {
        "type": "expression",
        "normative_status": "preferred",
        "designation": "red de transporte"
      }
    ],
    "language_code": "spa",
    "entry_status": "valid",
    "review_date": "2009-06-20 00:00:00 +0600",
    "review_decision_date": "2015-06-15 00:00:00 +0500",
    "review_decision_event": "Normal ISO processing",
    "status": "valid"
  },
  "swe": null,
  "zho": null
}