{
  "term": "association <UML>",
  "termid": "17",
  "eng": {
    "dates": [
      {
        "date": "2005-07-15 00:00:00 +0500",
        "type": "accepted"
      },
      {
        "date": "2015-07-01 00:00:00 +0500",
        "type": "amended"
      }
    ],
    "definition": [
      {
        "content": "semantic relationship between two or more classifiers that specifies connections among their instances"
      }
    ],
    "examples": [

    ],
    "id": "17",
    "notes": [
      {
        "content": "A binary association is an association among exactly two classifiers (including the possibility of an association from a classifier to itself)."
      }
    ],
    "release": -1.0,
    "sources": [
      {
        "origin": {
          "ref": "ISO/IEC 19501",
          "link": "https://www.iso.org/standard/32620.html"
        },
        "type": "authoritative",
        "status": "unspecified"
      },
      {
        "origin": {
          "ref": "ISO/TS 19103:2005 ,4.2.3"
        },
        "type": "lineage",
        "status": "unspecified"
      }
    ],
    "terms": [
      {
        "type": "expression",
        "designation": "association <UML>"
      }
    ],
    "language_code": "eng",
    "entry_status": "superseded",
    "review_date": "2009-08-31 00:00:00 +0600",
    "review_decision_date": "2015-07-01 00:00:00 +0500",
    "review_decision_event": "Publication of ISO 19150-2:2015(E)",
    "status": "superseded"
  },
  "ara": {
    "dates": [
      {
        "date": "2005-07-15 00:00:00 +0500",
        "type": "accepted"
      },
      {
        "date": "2015-07-01 00:00:00 +0500",
        "type": "amended"
      }
    ],
    "definition": [
      {
        "content": "العلاقة اللغوية القائمة بين مصنِّفَيْن أو أكثر \nالتي تحدد الترابط بين عناصرها"
      }
    ],
    "examples": [

    ],
    "id": "17",
    "notes": [
      {
        "content": "الربط الثنائي هو عبارة عن ربط بين مصنِّفَيْن بالضبط ( ويشمل ذلك إمكانية الربط من مصنِّف إلى نفسه)"
      }
    ],
    "release": -1.0,
    "sources": [
      {
        "origin": {
          "ref": "ISO/IEC 19501",
          "link": "https://www.iso.org/standard/32620.html"
        },
        "type": "authoritative",
        "status": "unspecified"
      },
      {
        "origin": {
          "ref": "ISO/TS 19103:2005 ,4.2.3"
        },
        "type": "lineage",
        "status": "unspecified"
      }
    ],
    "terms": [
      {
        "type": "expression",
        "designation": "ارتباط UML"
      },
      {
        "type": "abbreviation",
        "designation": ""
      }
    ],
    "language_code": "ara",
    "entry_status": "superseded",
    "review_date": "2009-08-31 00:00:00 +0600",
    "review_decision_date": "2015-07-01 00:00:00 +0500",
    "review_decision_event": "Publication of ISO 19150-2:2015(E)",
    "status": "superseded"
  },
  "dan": {
    "dates": [
      {
        "date": "2005-07-15 00:00:00 +0500",
        "type": "accepted"
      },
      {
        "date": "2015-07-01 00:00:00 +0500",
        "type": "amended"
      }
    ],
    "definition": [
      {
        "content": "semantisk sammenhæng imellem to eller flere klassifikatorer, som specificerer forbindelser mellem deres instanser"
      }
    ],
    "examples": [

    ],
    "id": "17",
    "notes": [
      {
        "content": "En binær association er en association imellem nøjagtig to klassifikatorer (inkl. muligheden for en association fra en klassifikator til sig selv)."
      }
    ],
    "release": -1.0,
    "sources": [
      {
        "origin": {
          "ref": "ISO/IEC 19501",
          "link": "https://www.iso.org/standard/32620.html"
        },
        "type": "authoritative",
        "status": "unspecified"
      },
      {
        "origin": {
          "ref": "ISO/TS 19103:2005 ,4.2.3"
        },
        "type": "lineage",
        "status": "unspecified"
      }
    ],
    "terms": [
      {
        "type": "expression",
        "designation": "association <UML>"
      }
    ],
    "language_code": "dan",
    "entry_status": "superseded",
    "review_date": "2009-08-31 00:00:00 +0600",
    "review_decision_date": "2015-07-01 00:00:00 +0500",
    "review_decision_event": "Publication of ISO 19150-2:2015(E)",
    "status": "superseded"
  },
  "deu": {
    "dates": [
      {
        "date": "2005-07-15 00:00:00 +0500",
        "type": "accepted"
      },
      {
        "date": "2015-07-01 00:00:00 +0500",
        "type": "amended"
      }
    ],
    "definition": [

    ],
    "examples": [

    ],
    "id": "17",
    "notes": [
      {
        "content": "A binary association is an association among exactly two classifiers (including the possibility of an association from a classifier to itself)."
      }
    ],
    "release": -1.0,
    "sources": [
      {
        "origin": {
          "ref": "ISO/IEC 19501",
          "link": "https://www.iso.org/standard/32620.html"
        },
        "type": "authoritative",
        "status": "unspecified"
      },
      {
        "origin": {
          "ref": "ISO/TS 19103:2005 ,4.2.3"
        },
        "type": "lineage",
        "status": "unspecified"
      }
    ],
    "terms": [
      {
        "type": "expression",
        "designation": "Relation <UML> (Synonym: Beziehung, Assoziation)"
      }
    ],
    "language_code": "deu",
    "entry_status": "superseded",
    "review_date": "2009-08-31 00:00:00 +0600",
    "review_decision_date": "2015-07-01 00:00:00 +0500",
    "review_decision_event": "Publication of ISO 19150-2:2015(E)",
    "status": "superseded"
  },
  "fin": {
    "dates": [
      {
        "date": "2005-07-15 00:00:00 +0500",
        "type": "accepted"
      },
      {
        "date": "2015-07-01 00:00:00 +0500",
        "type": "amended"
      }
    ],
    "definition": [
      {
        "content": "kahden tai useamman luokittelijan välinen semanttinen suhde, joka määrittää luokittelijoiden mukaisten ilmentymien väliset yhteydet"
      }
    ],
    "examples": [

    ],
    "id": "17",
    "notes": [
      {
        "content": "Binäärinen assosiaatio määrittää suhteen täsmälleen kahden luokittelijan välillä (mukaan lukien luokittelijan assosiaatiosuhde itseensä)."
      }
    ],
    "release": -1.0,
    "sources": [
      {
        "origin": {
          "ref": "ISO/IEC 19501",
          "link": "https://www.iso.org/standard/32620.html"
        },
        "type": "authoritative",
        "status": "unspecified"
      },
      {
        "origin": {
          "ref": "ISO/TS 19103:2005 ,4.2.3"
        },
        "type": "lineage",
        "status": "unspecified"
      }
    ],
    "terms": [
      {
        "type": "expression",
        "designation": "assosiaatio <UML>"
      },
      {
        "type": "expression",
        "designation": "assosiaatiosuhde <UML>"
      }
    ],
    "language_code": "fin",
    "entry_status": "superseded",
    "review_date": "2009-08-31 00:00:00 +0600",
    "review_decision_date": "2015-07-01 00:00:00 +0500",
    "review_decision_event": "Publication of ISO 19150-2:2015(E)",
    "status": "superseded"
  },
  "fra": {
    "dates": [
      {
        "date": "2005-07-15 00:00:00 +0500",
        "type": "accepted"
      },
      {
        "date": "2015-07-01 00:00:00 +0500",
        "type": "amended"
      }
    ],
    "definition": [
      {
        "content": "relation sémantique entre deux ou plusieurs classificateurs qui spécifient des connections parmi leurs instances"
      }
    ],
    "examples": [

    ],
    "id": "17",
    "notes": [

    ],
    "release": -1.0,
    "sources": [
      {
        "origin": {
          "ref": "ISO/IEC 19501",
          "link": "https://www.iso.org/standard/32620.html"
        },
        "type": "authoritative",
        "status": "unspecified"
      },
      {
        "origin": {
          "ref": "ISO/TS 19103:2005 ,4.2.3"
        },
        "type": "lineage",
        "status": "unspecified"
      }
    ],
    "terms": [
      {
        "type": "expression",
        "designation": "association <UML>"
      }
    ],
    "language_code": "fra",
    "entry_status": "superseded",
    "review_date": "2009-08-31 00:00:00 +0600",
    "review_decision_date": "2015-07-01 00:00:00 +0500",
    "review_decision_event": "Publication of ISO 19150-2:2015(E)",
    "status": "superseded"
  },
  "jpn": null,
  "kor": {
    "dates": [
      {
        "date": "2005-07-15 00:00:00 +0500",
        "type": "accepted"
      },
      {
        "date": "2015-07-01 00:00:00 +0500",
        "type": "amended"
      }
    ],
    "definition": [
      {
        "content": "인스턴스간의 연결을 규정하는 두 개 이상 분류자 간의 의미론적 관계"
      }
    ],
    "examples": [

    ],
    "id": "17",
    "notes": [
      {
        "content": "이진 연관 관계는 정확하게 두 분류자 간의 연관 관계이다."
      }
    ],
    "release": -1.0,
    "sources": [
      {
        "origin": {
          "ref": "ISO/IEC 19501",
          "link": "https://www.iso.org/standard/32620.html"
        },
        "type": "authoritative",
        "status": "unspecified"
      },
      {
        "origin": {
          "ref": "ISO/TS 19103:2005 ,4.2.3"
        },
        "type": "lineage",
        "status": "unspecified"
      }
    ],
    "terms": [
      {
        "type": "expression",
        "designation": "연관 <UML>"
      }
    ],
    "language_code": "kor",
    "entry_status": "superseded",
    "review_date": "2009-08-31 00:00:00 +0600",
    "review_decision_date": "2015-07-01 00:00:00 +0500",
    "review_decision_event": "Publication of ISO 19150-2:2015(E)",
    "status": "superseded"
  },
  "msa": null,
  "nld": null,
  "pol": null,
  "rus": {
    "dates": [
      {
        "date": "2005-07-15 00:00:00 +0500",
        "type": "accepted"
      }
    ],
    "definition": [
      {
        "content": "семантическое отношение двух или более классификаторов, определяющее взаимосвязи между их экземплярами"
      }
    ],
    "examples": [

    ],
    "id": "17",
    "notes": [
      {
        "content": "Бинарная ассоциация является ассоциацией  между  двумя классификаторами,  включая возможность ассоциации классификатора с самим собой"
      }
    ],
    "release": 1.0,
    "sources": [
      {
        "origin": {
          "ref": "ISO/IEC 19501",
          "link": "https://www.iso.org/standard/32620.html"
        },
        "type": "authoritative",
        "status": "unspecified"
      },
      {
        "origin": {
          "ref": "ISO/TS 19103:2005 ,4.2.3"
        },
        "type": "lineage",
        "status": "unspecified"
      }
    ],
    "terms": [
      {
        "type": "expression",
        "normative_status": "preferred",
        "designation": "ассоциация <UML>"
      }
    ],
    "language_code": "rus",
    "entry_status": "valid",
    "review_date": "2009-08-31 00:00:00 +0600",
    "status": "valid"
  },
  "spa": {
    "dates": [
      {
        "date": "2005-07-15 00:00:00 +0500",
        "type": "accepted"
      },
      {
        "date": "2015-07-01 00:00:00 +0500",
        "type": "amended"
      }
    ],
    "definition": [
      {
        "content": "relación semántica entre dos o más clasificadores que especifica conexiones entre sus instancias"
      }
    ],
    "examples": [

    ],
    "id": "17",
    "notes": [

    ],
    "release": -1.0,
    "sources": [
      {
        "origin": {
          "ref": "ISO/IEC 19501",
          "link": "https://www.iso.org/standard/32620.html"
        },
        "type": "authoritative",
        "status": "unspecified"
      },
      {
        "origin": {
          "ref": "ISO/TS 19103:2005 ,4.2.3"
        },
        "type": "lineage",
        "status": "unspecified"
      }
    ],
    "terms": [
      {
        "type": "expression",
        "designation": "asociación <UML>"
      }
    ],
    "language_code": "spa",
    "entry_status": "superseded",
    "review_date": "2009-08-31 00:00:00 +0600",
    "review_decision_date": "2015-07-01 00:00:00 +0500",
    "review_decision_event": "Publication of ISO 19150-2:2015(E)",
    "status": "superseded"
  },
  "swe": {
    "dates": [
      {
        "date": "2005-07-15 00:00:00 +0500",
        "type": "accepted"
      },
      {
        "date": "2015-07-01 00:00:00 +0500",
        "type": "amended"
      }
    ],
    "definition": [
      {
        "content": "UML-element som anger hur instanser kan eller ska referera till varandra"
      }
    ],
    "examples": [

    ],
    "id": "17",
    "notes": [
      {
        "content": "A binary association is an association among exactly two classifiers (including the possibility of an association from a classifier to itself)."
      }
    ],
    "release": -1.0,
    "sources": [
      {
        "origin": {
          "ref": "ISO/IEC 19501",
          "link": "https://www.iso.org/standard/32620.html"
        },
        "type": "authoritative",
        "status": "unspecified"
      },
      {
        "origin": {
          "ref": "ISO/TS 19103:2005 ,4.2.3"
        },
        "type": "lineage",
        "status": "unspecified"
      }
    ],
    "terms": [
      {
        "type": "expression",
        "designation": "samband <UML>"
      }
    ],
    "language_code": "swe",
    "entry_status": "superseded",
    "review_date": "2009-08-31 00:00:00 +0600",
    "review_decision_date": "2015-07-01 00:00:00 +0500",
    "review_decision_event": "Publication of ISO 19150-2:2015(E)",
    "status": "superseded"
  },
  "zho": {
    "dates": [
      {
        "date": "2005-07-15 00:00:00 +0500",
        "type": "accepted"
      },
      {
        "date": "2015-07-01 00:00:00 +0500",
        "type": "amended"
      }
    ],
    "definition": [
      {
        "content": "<UML>两个或两个以上类之间的语义关系，定义了类中实例间的连接。"
      }
    ],
    "examples": [

    ],
    "id": "17",
    "notes": [
      {
        "content": "二元关联确指两个类元之间的关联（包括一个类元与其本身的关联）"
      }
    ],
    "release": -1.0,
    "sources": [
      {
        "origin": {
          "ref": "ISO/IEC 19501",
          "link": "https://www.iso.org/standard/32620.html"
        },
        "type": "authoritative",
        "status": "unspecified"
      },
      {
        "origin": {
          "ref": "ISO/TS 19103:2005 ,4.2.3"
        },
        "type": "lineage",
        "status": "unspecified"
      }
    ],
    "terms": [
      {
        "type": "expression",
        "designation": "关联<UML>"
      }
    ],
    "language_code": "zho",
    "entry_status": "superseded",
    "review_date": "2009-08-31 00:00:00 +0600",
    "review_decision_date": "2015-07-01 00:00:00 +0500",
    "review_decision_event": "Publication of ISO 19150-2:2015(E)",
    "status": "superseded"
  }
}