{
  "term": "obsolete term",
  "termid": "315",
  "eng": {
    "dates": [
      {
        "date": "2008-11-15 00:00:00 +0500",
        "type": "accepted"
      }
    ],
    "definition": [
      {
        "content": "term which is no longer in common use"
      }
    ],
    "examples": [

    ],
    "id": "315",
    "notes": [

    ],
    "release": 2.0,
    "sources": [
      {
        "origin": {
          "ref": "ISO 1087-1:2000",
          "clause": "3.4.18",
          "link": "https://www.iso.org/standard/20057.html"
        },
        "type": "authoritative",
        "status": "unspecified"
      },
      {
        "origin": {
          "ref": "ISO/TS 19104:2008"
        },
        "type": "lineage",
        "status": "unspecified"
      }
    ],
    "terms": [
      {
        "type": "expression",
        "normative_status": "preferred",
        "designation": "obsolete term"
      }
    ],
    "language_code": "eng",
    "entry_status": "valid",
    "review_date": "2013-01-29 00:00:00 +0500",
    "review_decision_date": "2016-10-01 00:00:00 +0500",
    "review_decision_event": "Publication of ISO 19104:2016",
    "status": "valid"
  },
  "ara": {
    "dates": [
      {
        "date": "2008-11-15 00:00:00 +0500",
        "type": "accepted"
      }
    ],
    "definition": [
      {
        "content": "مصطلح لم يعد استعماله شائعا"
      }
    ],
    "examples": [

    ],
    "id": "315",
    "notes": [

    ],
    "release": 2.0,
    "sources": [
      {
        "origin": {
          "ref": "ISO 1087-1:2000",
          "clause": "3.4.18",
          "link": "https://www.iso.org/standard/20057.html"
        },
        "type": "authoritative",
        "status": "unspecified"
      },
      {
        "origin": {
          "ref": "ISO/TS 19104:2008"
        },
        "type": "lineage",
        "status": "unspecified"
      }
    ],
    "terms": [
      {
        "type": "expression",
        "normative_status": "preferred",
        "designation": "مصطلح بائد"
      }
    ],
    "language_code": "ara",
    "entry_status": "valid",
    "review_date": "2013-01-29 00:00:00 +0500",
    "review_decision_date": "2016-10-01 00:00:00 +0500",
    "review_decision_event": "Publication of ISO 19104:2016",
    "status": "valid"
  },
  "dan": null,
  "deu": {
    "dates": [
      {
        "date": "2008-11-15 00:00:00 +0500",
        "type": "accepted"
      }
    ],
    "definition": [

    ],
    "examples": [

    ],
    "id": "315",
    "notes": [

    ],
    "release": 2.0,
    "sources": [
      {
        "origin": {
          "ref": "ISO 1087-1:2000",
          "clause": "3.4.18",
          "link": "https://www.iso.org/standard/20057.html"
        },
        "type": "authoritative",
        "status": "unspecified"
      },
      {
        "origin": {
          "ref": "ISO/TS 19104:2008"
        },
        "type": "lineage",
        "status": "unspecified"
      }
    ],
    "terms": [
      {
        "type": "expression",
        "normative_status": "preferred",
        "designation": "überholter Begriff"
      }
    ],
    "language_code": "deu",
    "entry_status": "valid",
    "review_date": "2013-01-29 00:00:00 +0500",
    "review_decision_date": "2016-10-01 00:00:00 +0500",
    "review_decision_event": "Publication of ISO 19104:2016",
    "status": "valid"
  },
  "fin": null,
  "fra": null,
  "jpn": null,
  "kor": {
    "dates": [
      {
        "date": "2008-11-15 00:00:00 +0500",
        "type": "accepted"
      }
    ],
    "definition": [
      {
        "content": "더 이상 일반적으로 사용되지 않는 용어"
      }
    ],
    "examples": [

    ],
    "id": "315",
    "notes": [

    ],
    "release": 2.0,
    "sources": [
      {
        "origin": {
          "ref": "ISO 1087-1:2000",
          "clause": "3.4.18",
          "link": "https://www.iso.org/standard/20057.html"
        },
        "type": "authoritative",
        "status": "unspecified"
      },
      {
        "origin": {
          "ref": "ISO/TS 19104:2008"
        },
        "type": "lineage",
        "status": "unspecified"
      }
    ],
    "terms": [
      {
        "type": "expression",
        "normative_status": "preferred",
        "designation": "폐기된 용어"
      }
    ],
    "language_code": "kor",
    "entry_status": "valid",
    "review_date": "2013-01-29 00:00:00 +0500",
    "review_decision_date": "2016-10-01 00:00:00 +0500",
    "review_decision_event": "Publication of ISO 19104:2016",
    "status": "valid"
  },
  "msa": null,
  "nld": null,
  "pol": null,
  "rus": {
    "dates": [
      {
        "date": "2008-11-15 00:00:00 +0500",
        "type": "accepted"
      }
    ],
    "definition": [
      {
        "content": "термин, который больше не используется"
      }
    ],
    "examples": [

    ],
    "id": "315",
    "notes": [

    ],
    "release": 2.0,
    "sources": [
      {
        "origin": {
          "ref": "ISO 1087-1:2000",
          "link": "https://www.iso.org/standard/20057.html"
        },
        "type": "authoritative",
        "status": "unspecified"
      },
      {
        "origin": {
          "ref": "ISO/TS 19104:2008"
        },
        "type": "lineage",
        "status": "unspecified"
      }
    ],
    "terms": [
      {
        "type": "expression",
        "normative_status": "preferred",
        "designation": "устаревший термин"
      }
    ],
    "language_code": "rus",
    "entry_status": "valid",
    "status": "valid"
  },
  "spa": {
    "dates": [
      {
        "date": "2008-11-15 00:00:00 +0500",
        "type": "accepted"
      }
    ],
    "definition": [
      {
        "content": "término que ya no es de uso común"
      }
    ],
    "examples": [

    ],
    "id": "315",
    "notes": [

    ],
    "release": 2.0,
    "sources": [
      {
        "origin": {
          "ref": "ISO 1087-1:2000",
          "clause": "3.4.18",
          "link": "https://www.iso.org/standard/20057.html"
        },
        "type": "authoritative",
        "status": "unspecified"
      },
      {
        "origin": {
          "ref": "ISO/TS 19104:2008"
        },
        "type": "lineage",
        "status": "unspecified"
      }
    ],
    "terms": [
      {
        "type": "expression",
        "normative_status": "preferred",
        "designation": "término obsoleto"
      }
    ],
    "language_code": "spa",
    "entry_status": "valid",
    "review_date": "2013-01-29 00:00:00 +0500",
    "review_decision_date": "2016-10-01 00:00:00 +0500",
    "review_decision_event": "Publication of ISO 19104:2016",
    "status": "valid"
  },
  "swe": {
    "dates": [
      {
        "date": "2008-11-15 00:00:00 +0500",
        "type": "accepted"
      }
    ],
    "definition": [
      {
        "content": "term which is no longer in common use"
      }
    ],
    "examples": [

    ],
    "id": "315",
    "notes": [

    ],
    "release": 2.0,
    "sources": [
      {
        "origin": {
          "ref": "ISO 1087-1:2000",
          "clause": "3.4.18",
          "link": "https://www.iso.org/standard/20057.html"
        },
        "type": "authoritative",
        "status": "unspecified"
      },
      {
        "origin": {
          "ref": "ISO/TS 19104:2008"
        },
        "type": "lineage",
        "status": "unspecified"
      }
    ],
    "terms": [
      {
        "type": "expression",
        "normative_status": "preferred",
        "designation": "obsolete term"
      }
    ],
    "language_code": "swe",
    "entry_status": "valid",
    "review_date": "2013-01-29 00:00:00 +0500",
    "review_decision_date": "2016-10-01 00:00:00 +0500",
    "review_decision_event": "Publication of ISO 19104:2016",
    "status": "valid"
  },
  "zho": null
}