{
  "term": "ordinal temporal reference system",
  "termid": "323",
  "eng": {
    "dates": [
      {
        "date": "2002-09-01 00:00:00 +0600",
        "type": "accepted"
      }
    ],
    "definition": [
      {
        "content": "temporal reference system composed of ordinal eras"
      }
    ],
    "examples": [

    ],
    "id": "323",
    "notes": [

    ],
    "release": 1.0,
    "sources": [
      {
        "origin": {
          "ref": "ISO 19108:2002",
          "link": "https://www.iso.org/standard/26013.html"
        },
        "type": "authoritative"
      }
    ],
    "terms": [
      {
        "type": "expression",
        "normative_status": "preferred",
        "designation": "ordinal temporal reference system"
      }
    ],
    "language_code": "eng",
    "entry_status": "valid",
    "status": "valid"
  },
  "ara": {
    "dates": [
      {
        "date": "2002-09-01 00:00:00 +0600",
        "type": "accepted"
      }
    ],
    "definition": [
      {
        "content": "نظام مرجعي زمني مؤلف من حقب ترتيبية"
      }
    ],
    "examples": [

    ],
    "id": "323",
    "notes": [

    ],
    "release": 1.0,
    "sources": [
      {
        "origin": {
          "ref": "ISO 19108:2002",
          "link": "https://www.iso.org/standard/26013.html"
        },
        "type": "authoritative",
        "status": "unspecified"
      }
    ],
    "terms": [
      {
        "type": "expression",
        "normative_status": "preferred",
        "designation": "نظام مرجعي ترتيبي زمني"
      }
    ],
    "language_code": "ara",
    "entry_status": "valid",
    "status": "valid"
  },
  "dan": null,
  "deu": {
    "dates": [
      {
        "date": "2002-09-01 00:00:00 +0600",
        "type": "accepted"
      }
    ],
    "definition": [

    ],
    "examples": [

    ],
    "id": "323",
    "notes": [

    ],
    "release": 1.0,
    "sources": [
      {
        "origin": {
          "ref": "ISO 19108:2002",
          "link": "https://www.iso.org/standard/26013.html"
        },
        "type": "authoritative"
      }
    ],
    "terms": [
      {
        "type": "expression",
        "normative_status": "preferred",
        "designation": "zeitbezogenes Bezugssystem"
      }
    ],
    "language_code": "deu",
    "entry_status": "valid",
    "status": "valid"
  },
  "fin": {
    "dates": [
      {
        "date": "2002-09-01 00:00:00 +0600",
        "type": "accepted"
      }
    ],
    "definition": [
      {
        "content": "ajan vertausjärjestelmä, joka koostuu ordinaaliajanjaksoista"
      }
    ],
    "examples": [

    ],
    "id": "323",
    "notes": [

    ],
    "sources": [
      {
        "origin": {
          "ref": "ISO 19108:2002",
          "link": "https://www.iso.org/standard/26013.html"
        },
        "type": "authoritative",
        "status": "unspecified"
      },
      {
        "origin": {
          "ref": "Ei lähdettä, käännetty"
        },
        "type": "lineage"
      }
    ],
    "terms": [
      {
        "type": "expression",
        "normative_status": "preferred",
        "designation": "ordinaalinen ajan vertausjärjestelmä"
      }
    ],
    "language_code": "fin",
    "entry_status": "valid",
    "status": "valid"
  },
  "fra": {
    "dates": [
      {
        "date": "2002-09-01 00:00:00 +0600",
        "type": "accepted"
      }
    ],
    "definition": [
      {
        "content": "système de référence temporel composé d'ères ordinales"
      }
    ],
    "examples": [

    ],
    "id": "323",
    "notes": [

    ],
    "sources": [
      {
        "origin": {
          "ref": "ISO 19108",
          "link": "https://www.iso.org/standard/26013.html"
        },
        "type": "authoritative"
      },
      {
        "origin": {
          "ref": ""
        },
        "type": "lineage"
      }
    ],
    "terms": [
      {
        "type": "expression",
        "normative_status": "preferred",
        "designation": "système de référence temporel ordinal"
      }
    ],
    "language_code": "fra",
    "entry_status": "valid",
    "status": "valid"
  },
  "jpn": {
    "dates": [
      {
        "date": "2002-09-01 00:00:00 +0600",
        "type": "accepted"
      }
    ],
    "definition": [
      {
        "content": "順序年代の集合からなる時間参照系の一つ。順序尺度を基礎とする。"
      }
    ],
    "examples": [

    ],
    "id": "323",
    "notes": [

    ],
    "release": 1.0,
    "sources": [
      {
        "origin": {
          "ref": "ISO 19108:2002",
          "link": "https://www.iso.org/standard/26013.html"
        },
        "type": "authoritative",
        "status": "unspecified"
      },
      {
        "origin": {
          "ref": "JIS X 7108"
        },
        "type": "lineage"
      }
    ],
    "terms": [
      {
        "type": "expression",
        "normative_status": "preferred",
        "designation": "順序時間参照系"
      }
    ],
    "language_code": "jpn",
    "entry_status": "valid",
    "status": "valid"
  },
  "kor": {
    "dates": [
      {
        "date": "2007-11-01 00:00:00 +0500",
        "type": "accepted"
      }
    ],
    "definition": [
      {
        "content": "순서 연대의 계층 구조로 구성된 시간 참조 체계"
      }
    ],
    "examples": [

    ],
    "id": "323",
    "notes": [

    ],
    "release": 1.0,
    "sources": [
      {
        "origin": {
          "ref": "ISO 19108:2002",
          "link": "https://www.iso.org/standard/26013.html"
        },
        "type": "authoritative",
        "status": "unspecified"
      },
      {
        "origin": {
          "ref": "KS X ISO 19108"
        },
        "type": "lineage"
      }
    ],
    "terms": [
      {
        "type": "expression",
        "normative_status": "preferred",
        "designation": "서수 시간 참조 체계"
      }
    ],
    "language_code": "kor",
    "entry_status": "valid",
    "status": "valid"
  },
  "msa": null,
  "nld": null,
  "pol": {
    "dates": [
      {
        "date": "2002-09-01 00:00:00 +0600",
        "type": "accepted"
      }
    ],
    "definition": [
      {
        "content": "czasowy system odniesienia złożony z er porządkowych"
      }
    ],
    "examples": [

    ],
    "id": "323",
    "notes": [

    ],
    "release": 1.0,
    "sources": [
      {
        "origin": {
          "ref": "ISO 19108:2002",
          "link": "https://www.iso.org/standard/26013.html"
        },
        "type": "authoritative",
        "status": "unspecified"
      },
      {
        "origin": {
          "ref": "PN-EN ISO 19108"
        },
        "type": "lineage"
      }
    ],
    "terms": [
      {
        "type": "expression",
        "normative_status": "preferred",
        "designation": "porządkowy czasowy system odniesienia"
      }
    ],
    "language_code": "pol"
  },
  "rus": {
    "dates": [
      {
        "date": "2002-09-01 00:00:00 +0600",
        "type": "accepted"
      }
    ],
    "definition": [
      {
        "content": "система регистрации времени, составленная из порядковых эр"
      }
    ],
    "examples": [

    ],
    "id": "323",
    "notes": [

    ],
    "sources": [
      {
        "origin": {
          "ref": "ISO 19108:2002",
          "link": "https://www.iso.org/standard/26013.html"
        },
        "type": "authoritative",
        "status": "unspecified"
      },
      {
        "origin": {
          "ref": "Internet"
        },
        "type": "lineage"
      }
    ],
    "terms": [
      {
        "type": "expression",
        "normative_status": "preferred",
        "designation": "порядковая система отсчета времени"
      }
    ],
    "language_code": "rus",
    "entry_status": "valid",
    "status": "valid"
  },
  "spa": {
    "dates": [
      {
        "date": "2002-09-01 00:00:00 +0600",
        "type": "accepted"
      }
    ],
    "definition": [
      {
        "content": "sistema de referencia temporal que consta de eras ordinales"
      }
    ],
    "examples": [

    ],
    "id": "323",
    "notes": [

    ],
    "release": 1.0,
    "sources": [
      {
        "origin": {
          "ref": "ISO 19108:2002",
          "link": "https://www.iso.org/standard/26013.html"
        },
        "type": "authoritative"
      }
    ],
    "terms": [
      {
        "type": "expression",
        "normative_status": "preferred",
        "designation": "sistema de referencia temporal ordinal"
      }
    ],
    "language_code": "spa",
    "entry_status": "valid",
    "status": "valid"
  },
  "swe": {
    "dates": [
      {
        "date": "2002-09-01 00:00:00 +0600",
        "type": "accepted"
      }
    ],
    "definition": [
      {
        "content": "temporala referenssystem bestående av ordinaleror"
      }
    ],
    "examples": [

    ],
    "id": "323",
    "notes": [

    ],
    "release": 1.0,
    "sources": [
      {
        "origin": {
          "ref": "ISO 19108:2002",
          "link": "https://www.iso.org/standard/26013.html"
        },
        "type": "authoritative"
      },
      {
        "origin": {
          "ref": "(Type reference to national language document)"
        },
        "type": "lineage"
      }
    ],
    "terms": [
      {
        "type": "expression",
        "normative_status": "preferred",
        "designation": "ordinalt tidsreferenssystem"
      }
    ],
    "language_code": "swe",
    "entry_status": "valid",
    "status": "valid"
  },
  "zho": {
    "dates": [
      {
        "date": "2002-09-01 00:00:00 +0600",
        "type": "accepted"
      }
    ],
    "definition": [
      {
        "content": "由顺序时代构成的时间参照系。"
      }
    ],
    "examples": [

    ],
    "id": "323",
    "notes": [

    ],
    "sources": [
      {
        "origin": {
          "ref": "ISO 19108:2002",
          "link": "https://www.iso.org/standard/26013.html"
        },
        "type": "authoritative",
        "status": "unspecified"
      }
    ],
    "terms": [
      {
        "type": "expression",
        "normative_status": "preferred",
        "designation": "顺序时间参照系"
      }
    ],
    "language_code": "zho",
    "entry_status": "valid",
    "status": "valid"
  }
}