{
  "term": "rectified grid",
  "termid": "367",
  "eng": {
    "dates": [
      {
        "date": "2005-08-15 00:00:00 +0500",
        "type": "accepted"
      }
    ],
    "definition": [
      {
        "content": "grid for which there is an affine transformation between the grid coordinates and the coordinates of an external coordinate reference system"
      }
    ],
    "examples": [

    ],
    "id": "367",
    "notes": [
      {
        "content": "If the coordinate reference system is related to the earth by a datum, the grid is a georectified grid."
      }
    ],
    "release": 1.0,
    "sources": [
      {
        "origin": {
          "ref": "ISO 19123-1:2023",
          "clause": "3.1.42",
          "link": "https://www.iso.org/standard/70743.html"
        },
        "type": "authoritative"
      },
      {
        "origin": {
          "ref": "ISO 19123:2005"
        },
        "type": "lineage",
        "status": "unspecified"
      }
    ],
    "terms": [
      {
        "type": "expression",
        "normative_status": "preferred",
        "designation": "rectified grid"
      }
    ],
    "language_code": "eng",
    "entry_status": "valid",
    "review_date": "2023-06-21 00:00:00 +0500",
    "review_decision_date": "2023-06-21 00:00:00 +0500",
    "review_decision_event": "Publication of ISO 19123-1:2023(E)",
    "status": "valid"
  },
  "ara": {
    "dates": [
      {
        "date": "2005-08-15 00:00:00 +0500",
        "type": "accepted"
      }
    ],
    "definition": [
      {
        "content": "شبكة لها تحويل ارتباطي بين إحداثيات الشبكة وإحداثيات نظام إحداثيات مرجعي خارجي"
      }
    ],
    "examples": [

    ],
    "id": "367",
    "notes": [
      {
        "content": "إذا كان النظام الإحداثي المرجعي متصلاً بالأرض من خلال مرجع للإسناد , فإن شبكة التربيع تكون شبكة مصححة جغرافياً."
      }
    ],
    "release": 1.0,
    "sources": [
      {
        "origin": {
          "ref": "ISO 19123-1:2023",
          "clause": "3.1.42",
          "link": "https://www.iso.org/standard/70743.html"
        },
        "type": "authoritative"
      },
      {
        "origin": {
          "ref": "ISO 19123:2005"
        },
        "type": "lineage",
        "status": "unspecified"
      }
    ],
    "terms": [
      {
        "type": "expression",
        "normative_status": "preferred",
        "designation": "شبكة مصممه"
      }
    ],
    "language_code": "ara",
    "entry_status": "valid",
    "review_date": "2023-06-21 00:00:00 +0500",
    "review_decision_date": "2023-06-21 00:00:00 +0500",
    "review_decision_event": "Publication of ISO 19123-1:2023(E)",
    "status": "valid"
  },
  "dan": null,
  "deu": {
    "dates": [
      {
        "date": "2005-08-15 00:00:00 +0500",
        "type": "accepted"
      }
    ],
    "definition": [
      {
        "content": "Gitter, für das es eine Affintransformation zwischen den Gitterkoordinaten und den Koordinaten eines externen Koordinatensystems gibt"
      }
    ],
    "examples": [

    ],
    "id": "367",
    "notes": [
      {
        "content": "If the coordinate reference system is related to the earth by a datum, the grid is a georectified grid."
      }
    ],
    "release": 1.0,
    "sources": [
      {
        "origin": {
          "ref": "ISO 19123-1:2023",
          "clause": "3.1.42",
          "link": "https://www.iso.org/standard/70743.html"
        },
        "type": "authoritative"
      },
      {
        "origin": {
          "ref": "ISO 19123:2005"
        },
        "type": "lineage",
        "status": "unspecified"
      }
    ],
    "terms": [
      {
        "type": "expression",
        "normative_status": "preferred",
        "designation": "entzerrtes Gitter"
      }
    ],
    "language_code": "deu",
    "entry_status": "valid",
    "review_date": "2023-06-21 00:00:00 +0500",
    "review_decision_date": "2023-06-21 00:00:00 +0500",
    "review_decision_event": "Publication of ISO 19123-1:2023(E)",
    "status": "valid"
  },
  "fin": {
    "dates": [
      {
        "date": "2005-08-15 00:00:00 +0500",
        "type": "accepted"
      }
    ],
    "definition": [
      {
        "content": "hila, jolle on olemassa affiininen muunnos hilan koordinaattien ja ulkoisen koordinaattijärjestelmän koordinaattien välillä"
      }
    ],
    "examples": [

    ],
    "id": "367",
    "notes": [
      {
        "content": "Jos koordinaattijärjestelmä on datumin avulla liitetty Maahan, kyseessä on geo-oikaistu hila."
      }
    ],
    "release": 1.0,
    "sources": [
      {
        "origin": {
          "ref": "ISO 19123-1:2023",
          "clause": "3.1.42",
          "link": "https://www.iso.org/standard/70743.html"
        },
        "type": "authoritative"
      },
      {
        "origin": {
          "ref": "ISO 19123:2005"
        },
        "type": "lineage",
        "status": "unspecified"
      }
    ],
    "terms": [
      {
        "type": "expression",
        "normative_status": "preferred",
        "designation": "oikaistu hila"
      }
    ],
    "language_code": "fin",
    "entry_status": "valid",
    "review_date": "2023-06-21 00:00:00 +0500",
    "review_decision_date": "2023-06-21 00:00:00 +0500",
    "review_decision_event": "Publication of ISO 19123-1:2023(E)",
    "status": "valid"
  },
  "fra": {
    "dates": [
      {
        "date": "2005-08-15 00:00:00 +0500",
        "type": "accepted"
      }
    ],
    "definition": [
      {
        "content": "grille pour laquelle il y a une transformation affine entre les coordonnées dans la grille et les coordonnées dans un système de référence de coordonnées externe"
      }
    ],
    "examples": [

    ],
    "id": "367",
    "notes": [

    ],
    "release": 1.0,
    "sources": [
      {
        "origin": {
          "ref": "ISO 19123-1:2023",
          "clause": "3.1.42",
          "link": "https://www.iso.org/standard/70743.html"
        },
        "type": "authoritative"
      },
      {
        "origin": {
          "ref": "ISO 19123:2005"
        },
        "type": "lineage",
        "status": "unspecified"
      }
    ],
    "terms": [
      {
        "type": "expression",
        "normative_status": "preferred",
        "designation": "grille rectifiée"
      }
    ],
    "language_code": "fra",
    "entry_status": "valid",
    "review_date": "2023-06-21 00:00:00 +0500",
    "review_decision_date": "2023-06-21 00:00:00 +0500",
    "review_decision_event": "Publication of ISO 19123-1:2023(E)",
    "status": "valid"
  },
  "jpn": null,
  "kor": {
    "dates": [
      {
        "date": "2005-08-15 00:00:00 +0500",
        "type": "accepted"
      }
    ],
    "definition": [
      {
        "content": "격자 좌표와 외부 좌표 참조 체계의 좌표 간의 어파인 변환을 거친 격자"
      }
    ],
    "examples": [

    ],
    "id": "367",
    "notes": [
      {
        "content": "좌표 참조 체계가 데이텀에 의해 지구와 관련된다면, 해당 격자는 지리 정사 격자이다."
      }
    ],
    "release": 1.0,
    "sources": [
      {
        "origin": {
          "ref": "ISO 19123-1:2023",
          "clause": "3.1.42",
          "link": "https://www.iso.org/standard/70743.html"
        },
        "type": "authoritative"
      },
      {
        "origin": {
          "ref": "ISO 19123:2005"
        },
        "type": "lineage",
        "status": "unspecified"
      }
    ],
    "terms": [
      {
        "type": "expression",
        "normative_status": "preferred",
        "designation": "정사 격자"
      }
    ],
    "language_code": "kor",
    "entry_status": "valid",
    "review_date": "2023-06-21 00:00:00 +0500",
    "review_decision_date": "2023-06-21 00:00:00 +0500",
    "review_decision_event": "Publication of ISO 19123-1:2023(E)",
    "status": "valid"
  },
  "msa": null,
  "nld": null,
  "pol": {
    "dates": [
      {
        "date": "2005-08-15 00:00:00 +0500",
        "type": "accepted"
      }
    ],
    "definition": [
      {
        "content": "siatka, dla której istnieje transformacja afiniczna między jej współrzędnymi a współrzędnymi jakiegoś zewnętrznego systemu odniesień przestrzennych"
      }
    ],
    "examples": [

    ],
    "id": "367",
    "notes": [
      {
        "content": "Jeśli ten system odniesień przestrzennych jest powiązany z Ziemią przez układ odniesienia, to siatka jest siatką georektyfikowaną."
      }
    ],
    "release": 1.0,
    "sources": [
      {
        "origin": {
          "ref": "ISO 19123-1:2023",
          "clause": "3.1.42",
          "link": "https://www.iso.org/standard/70743.html"
        },
        "type": "authoritative"
      },
      {
        "origin": {
          "ref": "ISO 19123:2005"
        },
        "type": "lineage",
        "status": "unspecified"
      }
    ],
    "terms": [
      {
        "type": "expression",
        "normative_status": "preferred",
        "designation": "siatka zrektyfikowana"
      }
    ],
    "language_code": "pol",
    "review_date": "2023-06-21 00:00:00 +0500",
    "review_decision_date": "2023-06-21 00:00:00 +0500",
    "review_decision_event": "Publication of ISO 19123-1:2023(E)"
  },
  "rus": {
    "dates": [
      {
        "date": "2005-08-15 00:00:00 +0500",
        "type": "accepted"
      }
    ],
    "definition": [
      {
        "content": "сетка, для которой существует аффинное преобразование между сеточными координатами и координатами внешней координатной системы отсчета"
      }
    ],
    "examples": [

    ],
    "id": "367",
    "notes": [
      {
        "content": "Если координатная система отсчета привязана к Земле исходными датами, сетка является георектифицированной сеткой"
      }
    ],
    "release": 1.0,
    "sources": [
      {
        "origin": {
          "ref": "ISO 19123-1:2023",
          "clause": "3.1.42",
          "link": "https://www.iso.org/standard/70743.html"
        },
        "type": "authoritative"
      },
      {
        "origin": {
          "ref": "ISO 19123:2005"
        },
        "type": "lineage",
        "status": "unspecified"
      }
    ],
    "terms": [
      {
        "type": "expression",
        "normative_status": "preferred",
        "designation": "ректифицированная сетка"
      }
    ],
    "language_code": "rus",
    "entry_status": "retired",
    "review_date": "2023-06-21 00:00:00 +0500",
    "review_decision_date": "2023-06-21 00:00:00 +0500",
    "review_decision_event": "Publication of ISO 19123-1:2023(E)",
    "status": "retired"
  },
  "spa": {
    "dates": [
      {
        "date": "2005-08-15 00:00:00 +0500",
        "type": "accepted"
      }
    ],
    "definition": [
      {
        "content": "malla en la que hay una transformación afín entre las coordenadas de la malla y las coordenadas de un sistema de referencia de coordenadas externo"
      }
    ],
    "examples": [

    ],
    "id": "367",
    "notes": [
      {
        "content": "NOTA Si el sistema de referencia de coordenadas está relacionado mediante un datum con La Tierra, la malla es una malla georectificada."
      }
    ],
    "release": 1.0,
    "sources": [
      {
        "origin": {
          "ref": "ISO 19123-1:2023",
          "clause": "3.1.42",
          "link": "https://www.iso.org/standard/70743.html"
        },
        "type": "authoritative"
      },
      {
        "origin": {
          "ref": "ISO 19123:2005"
        },
        "type": "lineage",
        "status": "unspecified"
      }
    ],
    "terms": [
      {
        "type": "expression",
        "normative_status": "preferred",
        "designation": "malla rectificada"
      }
    ],
    "language_code": "spa",
    "entry_status": "valid",
    "review_date": "2023-06-21 00:00:00 +0500",
    "review_decision_date": "2023-06-21 00:00:00 +0500",
    "review_decision_event": "Publication of ISO 19123-1:2023(E)",
    "status": "valid"
  },
  "swe": {
    "dates": [
      {
        "date": "2005-08-15 00:00:00 +0500",
        "type": "accepted"
      }
    ],
    "definition": [
      {
        "content": "rutnät för vilket det finns en affin transformation mellan rutnätets koordinater och koordinaterna i ett externt koordinatsystem"
      }
    ],
    "examples": [

    ],
    "id": "367",
    "notes": [
      {
        "content": "En affin transformation tar hänsyn till bristande rätvinklighet mellan koordinataxlarna, olikheter i koordinatsystemens axelorientering, varierande skala i x- och y-led, olika placering av origo och hur koordinatsystemen är roterade i förhållande till varandra."
      }
    ],
    "release": 1.0,
    "sources": [
      {
        "origin": {
          "ref": "ISO 19123-1:2023",
          "clause": "3.1.42",
          "link": "https://www.iso.org/standard/70743.html"
        },
        "type": "authoritative"
      },
      {
        "origin": {
          "ref": "ISO 19123:2005"
        },
        "type": "lineage",
        "status": "unspecified"
      }
    ],
    "terms": [
      {
        "type": "expression",
        "normative_status": "preferred",
        "designation": "rektifierat rutnät"
      }
    ],
    "language_code": "swe",
    "entry_status": "valid",
    "review_date": "2023-06-21 00:00:00 +0500",
    "review_decision_date": "2023-06-21 00:00:00 +0500",
    "review_decision_event": "Publication of ISO 19123-1:2023(E)",
    "status": "valid"
  },
  "zho": {
    "dates": [
      {
        "date": "2005-08-15 00:00:00 +0500",
        "type": "accepted"
      }
    ],
    "definition": [
      {
        "content": "格网坐标和外部坐标参照系坐标之间存在仿射变换的格网。"
      }
    ],
    "examples": [

    ],
    "id": "367",
    "notes": [
      {
        "content": "如果某个坐标参照系通过基准与地球相关，该格网就是地理校正格网。"
      }
    ],
    "release": 1.0,
    "sources": [
      {
        "origin": {
          "ref": "ISO 19123-1:2023",
          "clause": "3.1.42",
          "link": "https://www.iso.org/standard/70743.html"
        },
        "type": "authoritative"
      },
      {
        "origin": {
          "ref": "ISO 19123:2005"
        },
        "type": "lineage",
        "status": "unspecified"
      }
    ],
    "terms": [
      {
        "type": "expression",
        "normative_status": "preferred",
        "designation": "校正格网"
      }
    ],
    "language_code": "zho",
    "entry_status": "valid",
    "review_date": "2023-06-21 00:00:00 +0500",
    "review_decision_date": "2023-06-21 00:00:00 +0500",
    "review_decision_event": "Publication of ISO 19123-1:2023(E)",
    "status": "valid"
  }
}