{
  "term": "Doppler shift",
  "termid": "991",
  "eng": {
    "dates": [
      {
        "date": "2010-06-15 00:00:00 +0500",
        "type": "accepted"
      }
    ],
    "definition": [
      {
        "content": "wavelength change resulting from relative motion of source and detector"
      }
    ],
    "examples": [

    ],
    "id": "991",
    "notes": [
      {
        "content": "In the SAR context, it is the frequency shift imposed on a radar signal due to relative motion between the transmitter and the object being illuminated."
      }
    ],
    "release": 2.0,
    "sources": [
      {
        "origin": {
          "ref": "ISO 19130-1:2018",
          "clause": "3.20",
          "link": "https://www.iso.org/standard/66847.html"
        },
        "type": "authoritative"
      },
      {
        "origin": {
          "ref": "ISO/TS 19130:2010"
        },
        "type": "lineage",
        "status": "unspecified"
      }
    ],
    "terms": [
      {
        "type": "expression",
        "normative_status": "preferred",
        "designation": "Doppler shift"
      }
    ],
    "language_code": "eng",
    "entry_status": "valid",
    "review_date": "2018-09-01 00:00:00 +0500",
    "review_decision_date": "2018-09-01 00:00:00 +0500",
    "review_decision_event": "Publication of ISO 19130-1:2018(E)",
    "status": "valid"
  },
  "ara": {
    "dates": [
      {
        "date": "2010-06-15 00:00:00 +0500",
        "type": "accepted"
      }
    ],
    "definition": [
      {
        "content": "تغيُّر في الطول الموجي ناتج عن الحركة النسبية للمصدر والكاشف"
      }
    ],
    "examples": [

    ],
    "id": "991",
    "notes": [
      {
        "content": "في سياق تقنية رادار الرصد المركب\"سار\" هي التحول في الترددات الذي يفرض على إشارة الرادار بسبب حركة نسبية بين جهاز البث والجسم الذي تجري إضاءته."
      }
    ],
    "release": 2.0,
    "sources": [
      {
        "origin": {
          "ref": "ISO 19130-1:2018",
          "clause": "3.20",
          "link": "https://www.iso.org/standard/66847.html"
        },
        "type": "authoritative"
      },
      {
        "origin": {
          "ref": "ISO/TS 19130:2010"
        },
        "type": "lineage",
        "status": "unspecified"
      }
    ],
    "terms": [
      {
        "type": "expression",
        "normative_status": "preferred",
        "designation": "تحول دوبلر"
      }
    ],
    "language_code": "ara",
    "entry_status": "valid",
    "review_date": "2018-09-01 00:00:00 +0500",
    "review_decision_date": "2018-09-01 00:00:00 +0500",
    "review_decision_event": "Publication of ISO 19130-1:2018(E)",
    "status": "valid"
  },
  "dan": null,
  "deu": {
    "dates": [
      {
        "date": "2010-06-15 00:00:00 +0500",
        "type": "accepted"
      }
    ],
    "definition": [
      {
        "content": "Wellenlängenänderung auf Grund der Relativbewegung zwischen Quelle und Detektor"
      }
    ],
    "examples": [

    ],
    "id": "991",
    "notes": [
      {
        "content": "In the SAR context, it is the frequency shift imposed on a radar signal due to relative motion between the transmitter and the object being illuminated."
      }
    ],
    "release": 2.0,
    "sources": [
      {
        "origin": {
          "ref": "ISO 19130-1:2018",
          "clause": "3.20",
          "link": "https://www.iso.org/standard/66847.html"
        },
        "type": "authoritative"
      },
      {
        "origin": {
          "ref": "ISO/TS 19130:2010"
        },
        "type": "lineage",
        "status": "unspecified"
      }
    ],
    "terms": [
      {
        "type": "expression",
        "normative_status": "preferred",
        "designation": "Doppler-Verschiebung"
      }
    ],
    "language_code": "deu",
    "entry_status": "valid",
    "review_date": "2018-09-01 00:00:00 +0500",
    "review_decision_date": "2018-09-01 00:00:00 +0500",
    "review_decision_event": "Publication of ISO 19130-1:2018(E)",
    "status": "valid"
  },
  "fin": null,
  "fra": null,
  "jpn": null,
  "kor": {
    "dates": [
      {
        "date": "2010-06-15 00:00:00 +0500",
        "type": "accepted"
      }
    ],
    "definition": [
      {
        "content": "소스와 탐지기의 상대적 움직임으로 인해 나타나는 파장의 변화"
      }
    ],
    "examples": [

    ],
    "id": "991",
    "notes": [
      {
        "content": "In the SAR context, it is the frequency shift imposed on a radar signal due to relative motion between the transmitter and the object being illuminated."
      }
    ],
    "release": 2.0,
    "sources": [
      {
        "origin": {
          "ref": "ISO 19130-1:2018",
          "clause": "3.20",
          "link": "https://www.iso.org/standard/66847.html"
        },
        "type": "authoritative"
      },
      {
        "origin": {
          "ref": "ISO/TS 19130:2010"
        },
        "type": "lineage",
        "status": "unspecified"
      }
    ],
    "terms": [
      {
        "type": "expression",
        "normative_status": "preferred",
        "designation": "도플러 이동"
      }
    ],
    "language_code": "kor",
    "entry_status": "valid",
    "review_date": "2018-09-01 00:00:00 +0500",
    "review_decision_date": "2018-09-01 00:00:00 +0500",
    "review_decision_event": "Publication of ISO 19130-1:2018(E)",
    "status": "valid"
  },
  "msa": {
    "dates": [
      {
        "date": "2010-06-15 00:00:00 +0500",
        "type": "accepted"
      }
    ],
    "definition": [

    ],
    "examples": [

    ],
    "id": "991",
    "notes": [
      {
        "content": "In the SAR context, it is the frequency shift imposed on a radar signal due to relative motion between the transmitter and the object being illuminated."
      }
    ],
    "release": 2.0,
    "sources": [
      {
        "origin": {
          "ref": "ISO 19130-1:2018",
          "clause": "3.20",
          "link": "https://www.iso.org/standard/66847.html"
        },
        "type": "authoritative"
      },
      {
        "origin": {
          "ref": "ISO/TS 19130:2010"
        },
        "type": "lineage",
        "status": "unspecified"
      }
    ],
    "terms": [
      {
        "type": "expression",
        "normative_status": "preferred",
        "designation": "anjakan doppler"
      }
    ],
    "language_code": "msa",
    "entry_status": "valid",
    "review_date": "2018-09-01 00:00:00 +0500",
    "review_decision_date": "2018-09-01 00:00:00 +0500",
    "review_decision_event": "Publication of ISO 19130-1:2018(E)",
    "status": "valid"
  },
  "nld": null,
  "pol": null,
  "rus": {
    "dates": [
      {
        "date": "2010-06-15 00:00:00 +0500",
        "type": "accepted"
      }
    ],
    "definition": [
      {
        "content": "изменение длины волны в результате относительного движения источника и приемника"
      }
    ],
    "examples": [

    ],
    "id": "991",
    "notes": [
      {
        "content": "В контексте SAR это частотный сдвиг, наложенный на радиолокационный сигнал из-за относительного движения между передатчиком и освещаемым объектом."
      }
    ],
    "release": 2.0,
    "sources": [
      {
        "origin": {
          "ref": "ISO 19130-1:2018",
          "clause": "3.20",
          "link": "https://www.iso.org/standard/66847.html"
        },
        "type": "authoritative"
      },
      {
        "origin": {
          "ref": "ISO/TS 19130:2010"
        },
        "type": "lineage",
        "status": "unspecified"
      }
    ],
    "terms": [
      {
        "type": "expression",
        "normative_status": "preferred",
        "designation": "Доплеровский сдвиг"
      }
    ],
    "language_code": "rus",
    "entry_status": "valid",
    "review_date": "2018-09-01 00:00:00 +0500",
    "review_decision_date": "2018-09-01 00:00:00 +0500",
    "review_decision_event": "Publication of ISO 19130-1:2018(E)",
    "status": "valid"
  },
  "spa": {
    "dates": [
      {
        "date": "2010-06-15 00:00:00 +0500",
        "type": "accepted"
      }
    ],
    "definition": [
      {
        "content": "cambio en la longitud de onda debido al movimiento relativo entre el objeto y el detector"
      }
    ],
    "examples": [

    ],
    "id": "991",
    "notes": [
      {
        "content": "NOTA En el contexto SAR, es el cambio de frecuencia que sufre una señal radar debido al movimiento relativo entre el transmisor y el objeto irradiado"
      }
    ],
    "release": 2.0,
    "sources": [
      {
        "origin": {
          "ref": "ISO 19130-1:2018",
          "clause": "3.20",
          "link": "https://www.iso.org/standard/66847.html"
        },
        "type": "authoritative"
      },
      {
        "origin": {
          "ref": "ISO/TS 19130:2010"
        },
        "type": "lineage",
        "status": "unspecified"
      }
    ],
    "terms": [
      {
        "type": "expression",
        "normative_status": "preferred",
        "designation": "efecto Doppler"
      }
    ],
    "language_code": "spa",
    "entry_status": "valid",
    "review_date": "2018-09-01 00:00:00 +0500",
    "review_decision_date": "2018-09-01 00:00:00 +0500",
    "review_decision_event": "Publication of ISO 19130-1:2018(E)",
    "status": "valid"
  },
  "swe": {
    "dates": [
      {
        "date": "2010-06-15 00:00:00 +0500",
        "type": "accepted"
      }
    ],
    "definition": [
      {
        "content": "ändring i observerad frekvens som beror på att den frekvensalstrande källan och observatören rör sig relativt varandra"
      }
    ],
    "examples": [

    ],
    "id": "991",
    "notes": [
      {
        "content": "In the SAR context, it is the frequency shift imposed on a radar signal due to relative motion between the transmitter and the object being illuminated."
      }
    ],
    "release": 2.0,
    "sources": [
      {
        "origin": {
          "ref": "ISO 19130-1:2018",
          "clause": "3.20",
          "link": "https://www.iso.org/standard/66847.html"
        },
        "type": "authoritative"
      },
      {
        "origin": {
          "ref": "ISO/TS 19130:2010"
        },
        "type": "lineage",
        "status": "unspecified"
      }
    ],
    "terms": [
      {
        "type": "expression",
        "normative_status": "preferred",
        "designation": "dopplereffekt"
      }
    ],
    "language_code": "swe",
    "entry_status": "valid",
    "review_date": "2018-09-01 00:00:00 +0500",
    "review_decision_date": "2018-09-01 00:00:00 +0500",
    "review_decision_event": "Publication of ISO 19130-1:2018(E)",
    "status": "valid"
  },
  "zho": null
}